{
  "dandiset": "001701",
  "asset": "sub-StickPin/sub-StickPin_ses-StickPin-DY09-g1_behavior+ecephys.nwb",
  "region_select": "MEC",
  "status": "ok",
  "n_units": 92,
  "duration_min": 30.21683483701204,
  "species": "Mus musculus",
  "region": "MEC (Entorhinal area medial part, dorsal zone)",
  "description": "X Maze",
  "subject": "StickPin",
  "frac_rhythmic": 0.2391304347826087,
  "n_rhythmic": 22,
  "median_peak_hz": 0.06863103953147875,
  "pc12_var": 0.20294843961939663,
  "pc12_z": 50.0040319583793,
  "p_pc12": 0.004975124378109453,
  "rot_z": 1.079633083087933,
  "p_rotation": 0.13930348258706468,
  "n_windows": 16,
  "n_sig_windows": 0,
  "oscillation_score": 0.0,
  "p_session": 1.0,
  "best_window_rot_z": 1.6940068752329933,
  "sequences": false
}