{
  "dandiset": "ebrains",
  "asset": "104638/OpenField",
  "region_select": "OpenField",
  "status": "ok",
  "n_units": 438,
  "duration_min": 25.5,
  "species": "Mus musculus",
  "region": "MEC - Layer 2, 3, 5 (Neuropixels 2.0)",
  "description": "OpenField",
  "subject": "104638",
  "frac_rhythmic": 0.7328767123287672,
  "n_rhythmic": 321,
  "median_peak_hz": 0.022368635106556043,
  "pc12_var": 0.19940282340722176,
  "pc12_z": 206.22477380582023,
  "p_pc12": 0.004975124378109453,
  "rot_z": -1.3774022275184779,
  "p_rotation": 0.8955223880597015,
  "n_windows": 13,
  "n_sig_windows": 1,
  "oscillation_score": 0.07692307692307693,
  "p_session": 0.48665791672049485,
  "best_window_rot_z": 2.664550040725236,
  "sequences": false
}